{
  "main": {
    "id": "c2f73675fd2d9297",
    "type": "split",
    "children": [
      {
        "id": "c89d6d8080bc8c2e",
        "type": "tabs",
        "children": [
          {
            "id": "01d987c96ac26e61",
            "type": "leaf",
            "pinned": true,
            "state": {
              "type": "markdown",
              "state": {
                "file": "README.md",
                "mode": "source",
                "source": false
              },
              "pinned": true
            }
          },
          {
            "id": "7167130ff9a17a2e",
            "type": "leaf",
            "pinned": true,
            "state": {
              "type": "markdown",
              "state": {
                "file": "todo.md",
                "mode": "source",
                "source": false
              },
              "pinned": true
            }
          }
        ],
        "currentTab": 1
      }
    ],
    "direction": "vertical"
  },
  "left": {
    "id": "ade3bdf722cdf7c9",
    "type": "split",
    "children": [
      {
        "id": "2f7d65cefc31b30e",
        "type": "tabs",
        "dimension": 48.10009267840593,
        "children": [
          {
            "id": "30ea3e619e5c4c61",
            "type": "leaf",
            "state": {
              "type": "file-explorer",
              "state": {
                "sortOrder": "alphabetical"
              }
            }
          },
          {
            "id": "6f438b765ba7a527",
            "type": "leaf",
            "state": {
              "type": "search",
              "state": {
                "query": "brownie",
                "matchingCase": false,
                "explainSearch": false,
                "collapseAll": false,
                "extraContext": false,
                "sortOrder": "alphabetical"
              }
            }
          },
          {
            "id": "af69588c8ee5a191",
            "type": "leaf",
            "state": {
              "type": "bookmarks",
              "state": {}
            }
          }
        ]
      },
      {
        "id": "70ae7f6205137ef4",
        "type": "tabs",
        "dimension": 51.899907321594064,
        "children": [
          {
            "id": "36d31c74556e5c4b",
            "type": "leaf",
            "state": {
              "type": "outline",
              "state": {
                "file": "todo.md"
              }
            }
          }
        ]
      }
    ],
    "direction": "horizontal",
    "width": 243.5
  },
  "right": {
    "id": "d79f2a8c3c60aaff",
    "type": "split",
    "children": [
      {
        "id": "4eb00ee7467f4ab4",
        "type": "tabs",
        "children": [
          {
            "id": "38598fd37de80536",
            "type": "leaf",
            "state": {
              "type": "backlink",
              "state": {
                "file": "todo.md",
                "collapseAll": false,
                "extraContext": false,
                "sortOrder": "alphabetical",
                "showSearch": false,
                "searchQuery": "",
                "backlinkCollapsed": false,
                "unlinkedCollapsed": true
              }
            }
          },
          {
            "id": "d46969a5c747abfc",
            "type": "leaf",
            "state": {
              "type": "outgoing-link",
              "state": {
                "file": "todo.md",
                "linksCollapsed": false,
                "unlinkedCollapsed": true
              }
            }
          },
          {
            "id": "59f6ca52057c0c10",
            "type": "leaf",
            "state": {
              "type": "tag",
              "state": {
                "sortOrder": "frequency",
                "useHierarchy": true
              }
            }
          }
        ],
        "currentTab": 2
      }
    ],
    "direction": "horizontal",
    "width": 300,
    "collapsed": true
  },
  "left-ribbon": {
    "hiddenItems": {
      "switcher:Open quick switcher": false,
      "graph:Open graph view": false,
      "canvas:Create new canvas": false,
      "daily-notes:Open today's daily note": false,
      "templates:Insert template": false,
      "command-palette:Open command palette": false
    }
  },
  "active": "7167130ff9a17a2e",
  "lastOpenFiles": [
    "Blurbs/Overflow.md",
    "LeetCode/278. First Bad Version.md",
    "todo.md",
    "README.md",
    "Blurbs/Python implementations of data structures.md",
    "!assets/attachments/Pasted image 20240304190105.png",
    "!assets/attachments/Pasted image 20240304190041.png",
    "!assets/attachments/Pasted image 20240304185920.png",
    "!assets/attachments/Pasted image 20240304185849.png",
    "Blurbs/Complexity of sorting.md",
    "Blurbs/Common combinatorial arguments in SWE.md",
    "Blurbs/0. README.md",
    "LeetCode/121. Best Time to Buy and Sell Stock.md",
    "!assets/attachments/Pasted image 20240304185345.png",
    "LeetCode/733. Flood Fill.md",
    "LeetCode/542. 01 Matrix.md",
    "Bugs/0. README.md",
    "LeetCode/125. Valid Palindrome.md",
    "!assets/attachments/Pasted image 20240304181642.png",
    "!assets/attachments/Pasted image 20240304181354.png",
    "!assets/attachments/Pasted image 20240304181309.png",
    "!assets/attachments/Pasted image 20240304181255.png",
    "!assets/attachments/Pasted image 20240304181027.png",
    "Blurbs",
    "LeetCode/217. Contains Duplicate.md",
    "Bugs/infinite loop caused by integer overflow.md",
    "Bugs",
    "LeetCode/226. Invert Binary Tree.md",
    "Calc/ana question.md",
    "LeetCode/232. Implement Queue using Stacks.md",
    "Calc/hw 4 solutions.md",
    "LeetCode/110. Balanced Binary Tree.md",
    "LeetCode/49. Group Anagrams.md",
    "LeetCode/973. K Closest Points to Origin.md",
    "LeetCode/15. 3Sum.md",
    "LeetCode/1046. Last Stone Weight.md",
    "LeetCode/1448. Count Good Nodes in Binary Tree.md",
    "Anki Card template wip/scratch.ipynb",
    "scratch.ipynb",
    "Anki Card template wip/scratch.py",
    "Calc",
    "LeetCode/py/973.py",
    "LeetCode/py/733.py",
    "LeetCode/py/704.py",
    "LeetCode/py/542.py"
  ]
}